{
  "os": "Windows-10-10.0.26100-SP0",
  "python": "CPython 3.11.5",
  "startedAt": "2025-09-13T07:09:13.993588Z",
  "program": "c:\\Users\\timvo\\OneDrive\\Documents\\VSC Projects\\CSE5ML\\Assessment 2\\TF_NN_MNIST\\CSE5ML_22843874_Assessment2_P1T1+3.ipynb",
  "codePath": "CSE5ML_22843874_Assessment2_P1T1+3.ipynb",
  "codePathLocal": "CSE5ML_22843874_Assessment2_P1T1+3.ipynb",
  "git": {
    "remote": "https://github.com/Sjakiesurfer1984/TF_NN_MNIST.git",
    "commit": "22d3bf9ad4b358fe45905c8c90b40b4e74076293"
  },
  "email": "tim.vos.nl@gmail.com",
  "root": "c:\\Users\\timvo\\OneDrive\\Documents\\VSC Projects\\CSE5ML\\Assessment 2\\TF_NN_MNIST\\wandb",
  "host": "LaptopVanTim",
  "executable": "c:\\Users\\timvo\\OneDrive\\Documents\\VSC Projects\\CSE5ML\\Assessment 2\\TF_NN_MNIST\\.venv\\Scripts\\python.exe",
  "cpu_count": 10,
  "cpu_count_logical": 12,
  "disk": {
    "/": {
      "total": "510873563136",
      "used": "358403252224"
    }
  },
  "memory": {
    "total": "16858472448"
  },
  "writerId": "dgt78t2yhpgq7s0lsbofc3y3t7otj2ro"
}